Annotatability/__init__.py
Annotatability/metrics.py
Annotatability/models.py
Annotatability-0.0.5.dist-info/LICENSE
Annotatability-0.0.5.dist-info/METADATA
Annotatability-0.0.5.dist-info/WHEEL
Annotatability-0.0.5.dist-info/top_level.txt
Annotatability-0.0.5.dist-info/RECORD
